<kaspi_catalog date="&lt;function now at 0x7f20eaa32e50&gt;" xmlns="kaspiShopping" xmlns:xsi="http://www.w3.org/2001/XMLSchema-instance" xsi:schemaLocation="kaspiShopping http://kaspi.kz/kaspishopping.xsd"><company>Kartina-Almaty</company><merchantid>8016003</merchantid><offers><offer sku="104725965"><model>Kartina Almaty &#1082;&#1072;&#1088;&#1090;&#1080;&#1085;&#1072; &#1043;&#1091;&#1089;&#1090;&#1072;&#1074; &#1050;&#1083;&#1080;&#1084;&#1090; &#1058;&#1088;&#1080;&#1087;&#1090;&#1080;&#1093; 60x90 &#1089;&#1084;</model><brand>Kartina Almaty</brand><availabilities><availability storeId="PP1" available="yes" /></availabilities><price>12969</price></offer><offer sku="101870698"><model>iPhone 6 32&#1058;&#1086;&#1088;&#1088;&#1080;&#1085;&#1072; &#1043;&#1086;&#1088;&#1085;&#1099;&#1081; &#1087;&#1077;&#1081;&#1079;&#1072;&#1078; 200x99 &#1089;&#1084; GB Black</model><brand>&#1058;&#1086;&#1088;&#1088;&#1080;&#1085;&#1072;</brand><availabilities><availability storeId="PP1" available="yes" /></availabilities><price>22159</price></offer><offer sku="101967477"><model>Seven Art 1801 &#1048;&#1075;&#1088;&#1072; &#1090;&#1077;&#1085;&#1077;&#1081; 150x78 &#1089;&#1084;</model><brand>Seven Art </brand><availabilities><availability storeId="PP1" available="yes" /></availabilities><price>20629</price></offer><offer sku="103131439"><model>Seven Art &#1084;&#1086;&#1076;&#1091;&#1083;&#1100;&#1085;&#1072;&#1103; &#1082;&#1072;&#1088;&#1090;&#1080;&#1085;&#1072; &#1058;&#1088;&#1080; &#1084;&#1091;&#1076;&#1088;&#1099;&#1077; &#1086;&#1073;&#1077;&#1079;&#1100;&#1103;&#1085;&#1099; 100x60 &#1089;&#1084;</model><brand>Seven Art</brand><availabilities><availability storeId="PP1" available="yes" /></availabilities><price>9130</price></offer><offer sku="105819561"><model>PROFI DECOR &#1082;&#1072;&#1088;&#1090;&#1080;&#1085;&#1072; &#1044;&#1088;&#1077;&#1074;&#1086; &#1089;&#1095;&#1072;&#1089;&#1090;&#1100;&#1103; 120x80 &#1089;&#1084;</model><brand>PROFI DECOR</brand><availabilities><availability storeId="PP1" available="yes" /></availabilities><price>11297</price></offer><offer sku="105169856"><model>PROFI DECOR &#1084;&#1086;&#1076;&#1091;&#1083;&#1100;&#1085;&#1072;&#1103; &#1082;&#1072;&#1088;&#1090;&#1080;&#1085;&#1072; &#1040;&#1085;&#1090;&#1080;&#1095;&#1085;&#1099;&#1077; &#1074;&#1088;&#1077;&#1084;&#1077;&#1085;&#1072; 130x65 &#1089;&#1084;</model><brand>PROFI DECOR</brand><availabilities><availability storeId="PP1" available="yes" /></availabilities><price>11687</price></offer><offer sku="103657917"><model>PROFI DECOR &#1084;&#1086;&#1076;&#1091;&#1083;&#1100;&#1085;&#1072;&#1103; &#1082;&#1072;&#1088;&#1090;&#1080;&#1085;&#1072; &#1047;&#1086;&#1083;&#1086;&#1090;&#1099;&#1077; &#1086;&#1083;&#1077;&#1085;&#1080; 130x65 &#1089;&#1084;</model><brand>PROFI DECOR</brand><availabilities><availability storeId="PP1" available="yes" /></availabilities><price>10896</price></offer><offer sku="103263755"><model>PROFI DECOR &#1084;&#1086;&#1076;&#1091;&#1083;&#1100;&#1085;&#1072;&#1103; &#1082;&#1072;&#1088;&#1090;&#1080;&#1085;&#1072; &#1040;&#1092;&#1088;&#1080;&#1082;&#1072;&#1085;&#1082;&#1072; &#1080; &#1047;&#1086;&#1083;&#1086;&#1090;&#1099;&#1077; &#1059;&#1082;&#1088;&#1072;&#1096;&#1077;&#1085;&#1080;&#1103; 100x50 &#1089;&#1084;</model><brand>PROFI DECOR</brand><availabilities><availability storeId="PP1" available="yes" /></availabilities><price>9896</price></offer><offer sku="102995544"><model>Seven Art &#1084;&#1086;&#1076;&#1091;&#1083;&#1100;&#1085;&#1072;&#1103; &#1082;&#1072;&#1088;&#1090;&#1080;&#1085;&#1072; &#1041;&#1077;&#1083;&#1099;&#1081; &#1083;&#1077;&#1074; &#1074; &#1075;&#1086;&#1088;&#1072;&#1093; 140x80 &#1089;&#1084;</model><brand>Seven Art</brand><availabilities><availability storeId="PP1" available="yes" /></availabilities><price>13798</price></offer><offer sku="&#160;103657898"><model>PROFI DECOR &#1084;&#1086;&#1076;&#1091;&#1083;&#1100;&#1085;&#1072;&#1103; &#1082;&#1072;&#1088;&#1090;&#1080;&#1085;&#1072; &#1042;&#1054;&#1057;&#1061;&#1048;&#1058;&#1048;&#1058;&#1045;&#1051;&#1068;&#1053;&#1067;&#1049; &#1058;&#1056;&#1048;&#1055;&#1058;&#1048;&#1061; 200x100 &#1089;&#1084;</model><brand>PROFI DECOR</brand><availabilities><availability storeId="PP1" available="yes" /></availabilities><price>14983</price></offer><offer sku="102370874"><model>&#1058;&#1086;&#1088;&#1088;&#1080;&#1085;&#1072; &#1058;&#1072;&#1073;&#1091;&#1085; &#1083;&#1086;&#1096;&#1072;&#1076;&#1077;&#1081; 99&#1093;170&#1089;&#1084;</model><brand>&#1058;&#1086;&#1088;&#1088;&#1080;&#1085;&#1072;</brand><availabilities><availability storeId="PP1" available="yes" /></availabilities><price>16588</price></offer><offer sku="104248022"><model>&#1058;&#1086;&#1088;&#1088;&#1080;&#1085;&#1072; &#1084;&#1086;&#1076;&#1091;&#1083;&#1100;&#1085;&#1072;&#1103; &#1082;&#1072;&#1088;&#1090;&#1080;&#1085;&#1072; &#1044;&#1077;&#1085;&#1077;&#1078;&#1085;&#1086;&#1077; &#1076;&#1077;&#1088;&#1077;&#1074;&#1086; 104x54 &#1089;&#1084;</model><brand>&#1058;&#1086;&#1088;&#1088;&#1080;&#1085;&#1072;</brand><availabilities><availability storeId="PP1" available="yes" /></availabilities><price>10755</price></offer><offer sku="102370876"><model>&#1048;&#1055; &#1058;&#1086;&#1088;&#1088;&#1080;&#1085;&#1072; &#1084;&#1086;&#1076;&#1091;&#1083;&#1100;&#1085;&#1072;&#1103; &#1082;&#1072;&#1088;&#1090;&#1080;&#1085;&#1072; &#1040;&#1073;&#1089;&#1090;&#1088;&#1072;&#1082;&#1094;&#1080;&#1103; &#1079;&#1086;&#1083;&#1086;&#1090;&#1086; 171x84 &#1089;&#1084; + &#1087;&#1086;&#1082;&#1088;&#1099;&#1090;&#1080;&#1077; &#1083;&#1072;&#1082;&#1086;&#1084;, &#1089; &#1101;&#1092;&#1092;&#1077;&#1082;&#1090;&#1086;&#1084; &#1072;&#1083;&#1084;&#1072;&#1079;&#1085;&#1086;&#1081; &#1087;&#1099;&#1083;&#1080;</model><brand>&#1058;&#1086;&#1088;&#1088;&#1080;&#1085;&#1072;</brand><availabilities><availability storeId="PP1" available="yes" /></availabilities><price>14372</price></offer><offer sku="105896849"><model>&#1058;&#1086;&#1088;&#1088;&#1080;&#1085;&#1072; &#1084;&#1086;&#1076;&#1091;&#1083;&#1100;&#1085;&#1072;&#1103; &#1082;&#1072;&#1088;&#1090;&#1080;&#1085;&#1072; &#1040;&#1073;&#1089;&#1090;&#1088;&#1072;&#1082;&#1094;&#1080;&#1103; 108x54 &#1089;&#1084;</model><brand>&#1058;&#1086;&#1088;&#1088;&#1080;&#1085;&#1072;</brand><availabilities><availability storeId="PP1" available="yes" /></availabilities><price>13312</price></offer><offer sku="105915275"><model>&#1058;&#1086;&#1088;&#1088;&#1080;&#1085;&#1072; &#1084;&#1086;&#1076;&#1091;&#1083;&#1100;&#1085;&#1072;&#1103; &#1082;&#1072;&#1088;&#1090;&#1080;&#1085;&#1072; &#1040;&#1073;&#1089;&#1090;&#1088;&#1072;&#1082;&#1094;&#1080;&#1103; &#1079;&#1086;&#1083;&#1086;&#1090;&#1086;&#1084; 100x50 &#1089;&#1084;</model><brand>&#1058;&#1086;&#1088;&#1088;&#1080;&#1085;&#1072;</brand><availabilities><availability storeId="PP1" available="yes" /></availabilities><price>12770</price></offer><offer sku="104248031"><model>&#1048;&#1055; &#1058;&#1086;&#1088;&#1088;&#1080;&#1085;&#1072; &#1084;&#1086;&#1076;&#1091;&#1083;&#1100;&#1085;&#1072;&#1103; &#1082;&#1072;&#1088;&#1090;&#1080;&#1085;&#1072; &#1044;&#1077;&#1085;&#1077;&#1078;&#1085;&#1086;&#1077; &#1076;&#1077;&#1088;&#1077;&#1074;&#1086; 190x99 &#1089;&#1084; + &#1087;&#1086;&#1082;&#1088;&#1099;&#1090;&#1080;&#1077; &#1083;&#1072;&#1082;&#1086;&#1084; &#1089; &#1101;&#1092;&#1092;&#1077;&#1082;&#1090;&#1086;&#1084; &#1072;&#1083;&#1084;&#1072;&#1079;&#1085;&#1086;&#1081; &#1087;&#1099;&#1083;&#1080;</model><brand>&#1058;&#1086;&#1088;&#1088;&#1080;&#1085;&#1072;</brand><availabilities><availability storeId="PP1" available="yes" /></availabilities><price>23323</price></offer><offer sku="103657944"><model>PROFI DECOR &#1084;&#1086;&#1076;&#1091;&#1083;&#1100;&#1085;&#1072;&#1103; &#1082;&#1072;&#1088;&#1090;&#1080;&#1085;&#1072; &#1044;&#1088;&#1077;&#1074;&#1086; &#1074; &#1079;&#1086;&#1083;&#1086;&#1090;&#1077; 80x60 &#1089;&#1084;</model><brand>PROFI DECOR</brand><availabilities><availability storeId="PP1" available="yes" /></availabilities><price>10657</price></offer><offer sku="&#160;103384184"><model>&#1058;&#1086;&#1088;&#1088;&#1080;&#1085;&#1072; &#1084;&#1086;&#1076;&#1091;&#1083;&#1100;&#1085;&#1072;&#1103; &#1082;&#1072;&#1088;&#1090;&#1080;&#1085;&#1072; &#1051;&#1077;&#1074; 180x99 &#1089;&#1084;</model><brand>&#1058;&#1086;&#1088;&#1088;&#1080;&#1085;&#1072;</brand><availabilities><availability storeId="PP1" available="yes" /></availabilities><price>20289</price></offer><offer sku="103384003"><model>&#1048;&#1055; &#1058;&#1086;&#1088;&#1088;&#1080;&#1085;&#1072; &#1084;&#1086;&#1076;&#1091;&#1083;&#1100;&#1085;&#1072;&#1103; &#1082;&#1072;&#1088;&#1090;&#1080;&#1085;&#1072; &#1051;&#1086;&#1096;&#1072;&#1076;&#1080; 150x84 &#1089;&#1084; + &#1087;&#1086;&#1082;&#1088;&#1099;&#1090;&#1080;&#1077; &#1083;&#1072;&#1082;&#1086;&#1084; &#1089; &#1101;&#1092;&#1092;&#1077;&#1082;&#1090;&#1086;&#1084; &#1072;&#1083;&#1084;&#1072;&#1079;&#1085;&#1086;&#1081; &#1087;&#1099;&#1083;&#1080;</model><brand>&#1058;&#1086;&#1088;&#1088;&#1080;&#1085;&#1072;</brand><availabilities><availability storeId="PP1" available="yes" /></availabilities><price>17180</price></offer><offer sku="103263776"><model>PROFI DECOR &#1084;&#1086;&#1076;&#1091;&#1083;&#1100;&#1085;&#1072;&#1103; &#1082;&#1072;&#1088;&#1090;&#1080;&#1085;&#1072; &#1040;&#1092;&#1088;&#1080;&#1082;&#1072;&#1085;&#1082;&#1072; &#1080; &#1047;&#1086;&#1083;&#1086;&#1090;&#1099;&#1077; &#1059;&#1082;&#1088;&#1072;&#1096;&#1077;&#1085;&#1080;&#1103; 150x75 &#1089;&#1084;</model><brand>PROFI DECOR</brand><availabilities><availability storeId="PP1" available="yes" /></availabilities><price>16783</price></offer><offer sku="103163173"><model>&#1048;&#1055; &#1058;&#1086;&#1088;&#1088;&#1080;&#1085;&#1072; &#1084;&#1086;&#1076;&#1091;&#1083;&#1100;&#1085;&#1072;&#1103; &#1082;&#1072;&#1088;&#1090;&#1080;&#1085;&#1072; &#1062;&#1074;&#1077;&#1090;&#1099; 152x84 &#1089;&#1084; + &#1087;&#1086;&#1082;&#1088;&#1099;&#1090;&#1080;&#1077; &#1083;&#1072;&#1082;&#1086;&#1084; &#1089; &#1101;&#1092;&#1092;&#1077;&#1082;&#1090;&#1086;&#1084; &#1072;&#1083;&#1084;&#1072;&#1079;&#1085;&#1086;&#1081; &#1087;&#1099;&#1083;&#1080;</model><brand>&#1058;&#1086;&#1088;&#1088;&#1080;&#1085;&#1072;</brand><availabilities><availability storeId="PP1" available="yes" /></availabilities><price>20749</price></offer><offer sku="103168181"><model>&#1048;&#1055; &#1058;&#1086;&#1088;&#1088;&#1080;&#1085;&#1072; &#1084;&#1086;&#1076;&#1091;&#1083;&#1100;&#1085;&#1072;&#1103; &#1082;&#1072;&#1088;&#1090;&#1080;&#1085;&#1072; &#1047;&#1091;&#1073; 150x99 &#1089;&#1084; + &#1087;&#1086;&#1082;&#1088;&#1099;&#1090;&#1080;&#1077; &#1083;&#1072;&#1082;&#1086;&#1084; &#1089; &#1101;&#1092;&#1092;&#1077;&#1082;&#1090;&#1086;&#1084; &#1072;&#1083;&#1084;&#1072;&#1079;&#1085;&#1086;&#1081; &#1087;&#1099;&#1083;&#1080;</model><brand>&#1058;&#1086;&#1088;&#1088;&#1080;&#1085;&#1072;</brand><availabilities><availability storeId="PP1" available="yes" /></availabilities><price>17632</price></offer><offer sku="101887163"><model>Press House &#1047;&#1086;&#1083;&#1086;&#1090;&#1086;&#1081; &#1087;&#1072;&#1087;&#1086;&#1088;&#1086;&#1090;&#1085;&#1080;&#1082; 30&#1093;42 &#1089;&#1084;</model><brand>Press House</brand><availabilities><availability storeId="PP1" available="yes" /></availabilities><price>10747</price></offer><offer sku="102937786"><model>&#1048;&#1055; &#1058;&#1086;&#1088;&#1088;&#1080;&#1085;&#1072; &#1084;&#1086;&#1076;&#1091;&#1083;&#1100;&#1085;&#1072;&#1103; &#1082;&#1072;&#1088;&#1090;&#1080;&#1085;&#1072; &#1050;&#1072;&#1072;&#1073;&#1072; 149x99 &#1089;&#1084; + &#1087;&#1086;&#1082;&#1088;&#1099;&#1090;&#1080;&#1077; &#1083;&#1072;&#1082;&#1086;&#1084; &#1089; &#1101;&#1092;&#1092;&#1077;&#1082;&#1090;&#1086;&#1084; &#1072;&#1083;&#1084;&#1072;&#1079;&#1085;&#1086;&#1081; &#1087;&#1099;&#1083;&#1080;</model><brand>&#1058;&#1086;&#1088;&#1088;&#1080;&#1085;&#1072;</brand><availabilities><availability storeId="PP1" available="yes" /></availabilities><price>20217</price></offer><offer sku="103881928"><model>Kartina Almaty &#1084;&#1086;&#1076;&#1091;&#1083;&#1100;&#1085;&#1072;&#1103; &#1082;&#1072;&#1088;&#1090;&#1080;&#1085;&#1072; &#1043;&#1086;&#1088;&#1085;&#1099;&#1081; &#1087;&#1077;&#1081;&#1079;&#1072;&#1078; 180x99 &#1089;&#1084;</model><brand>Kartina Almaty</brand><availabilities><availability storeId="PP1" available="yes" /></availabilities><price>20997</price></offer><offer sku="104757476"><model>Mebel Pro &#1087;&#1086;&#1089;&#1090;&#1077;&#1088; &#1057;&#1090;&#1080;&#1083;&#1100;&#1085;&#1099;&#1081; &#1083;&#1077;&#1074; 55x85 &#1089;&#1084;</model><brand>Mebel Pro</brand><availabilities><availability storeId="PP1" available="yes" /></availabilities><price>13898</price></offer><offer sku="104790621"><model>Artstudio Mosaic &#1082;&#1072;&#1088;&#1090;&#1080;&#1085;&#1072; &#1044;&#1072;&#1074;&#1080;&#1076; 70x100 &#1089;&#1084;</model><brand>Artstudio</brand><availabilities><availability storeId="PP1" available="yes" /></availabilities><price>11895</price></offer><offer sku="&#160;104790615"><model>Artstudio Mosaic &#1082;&#1072;&#1088;&#1090;&#1080;&#1085;&#1072; &#1044;&#1072;&#1074;&#1080;&#1076; 70x100 &#1089;&#1084;</model><brand>Artstudio</brand><availabilities><availability storeId="PP1" available="yes" /></availabilities><price>13998</price></offer><offer sku="&#160;104790613"><model>Artstudio Mosaic &#1084;&#1086;&#1076;&#1091;&#1083;&#1100;&#1085;&#1072;&#1103; &#1082;&#1072;&#1088;&#1090;&#1080;&#1085;&#1072; &#1040;&#1092;&#1088;&#1080;&#1082;&#1072;&#1085;&#1089;&#1082;&#1072;&#1103; &#1078;&#1077;&#1085;&#1097;&#1080;&#1085;&#1072; 90x40 &#1089;&#1084;</model><brand>Artstudio</brand><availabilities><availability storeId="PP1" available="yes" /></availabilities><price>14393</price></offer><offer sku="104778525"><model>&#1058;&#1086;&#1088;&#1088;&#1080;&#1085;&#1072; &#1084;&#1086;&#1076;&#1091;&#1083;&#1100;&#1085;&#1072;&#1103; &#1082;&#1072;&#1088;&#1090;&#1080;&#1085;&#1072; &#1040;&#1085;&#1075;&#1077;&#1083; 96x54 &#1089;&#1084;</model><brand>&#1058;&#1086;&#1088;&#1088;&#1080;&#1085;&#1072;</brand><availabilities><availability storeId="PP1" available="yes" /></availabilities><price>12521</price></offer><offer sku="104509709"><model>Kartina Almaty &#1084;&#1086;&#1076;&#1091;&#1083;&#1100;&#1085;&#1072;&#1103; &#1082;&#1072;&#1088;&#1090;&#1080;&#1085;&#1072; &#1042;&#1054;&#1057;&#1061;&#1048;&#1058;&#1048;&#1058;&#1045;&#1051;&#1068;&#1053;&#1067;&#1049; &#1058;&#1056;&#1048;&#1055;&#1058;&#1048;&#1061; 120x60 &#1089;&#1084;</model><brand>Kartina Almaty</brand><availabilities><availability storeId="PP1" available="yes" /></availabilities><price>14853</price></offer><offer sku="104529201"><model>Mebel Pro &#1087;&#1086;&#1089;&#1090;&#1077;&#1088; &#1042;&#1079;&#1075;&#1083;&#1103;&#1076; &#1087;&#1072;&#1085;&#1090;&#1077;&#1088;&#1099; 55x90 &#1089;&#1084;</model><brand>Mebel Pro</brand><availabilities><availability storeId="PP1" available="yes" /></availabilities><price>12897</price></offer><offer sku="105558893"><model>ModulPrint &#1087;&#1086;&#1089;&#1090;&#1077;&#1088; &#1047;&#1086;&#1083;&#1086;&#1090;&#1086;&#1081; &#1076;&#1086;&#1083;&#1083;&#1072;&#1088; 120x55 &#1089;&#1084;</model><brand>ModulPrint</brand><availabilities><availability storeId="PP1" available="yes" /></availabilities><price>10552</price></offer><offer sku="104294188"><model>&#1048;&#1055; &#1058;&#1086;&#1088;&#1088;&#1080;&#1085;&#1072; &#1084;&#1086;&#1076;&#1091;&#1083;&#1100;&#1085;&#1072;&#1103; &#1082;&#1072;&#1088;&#1090;&#1080;&#1085;&#1072; &#1040;&#1088;&#1090; &#1083;&#1080;&#1089;&#1090;&#1100;&#1103; 180x84 &#1089;&#1084; + &#1087;&#1086;&#1082;&#1088;&#1099;&#1090;&#1080;&#1077; &#1083;&#1072;&#1082;&#1086;&#1084; &#1089; &#1101;&#1092;&#1092;&#1077;&#1082;&#1090;&#1086;&#1084; &#1072;&#1083;&#1084;&#1072;&#1079;&#1085;&#1086;&#1081; &#1087;&#1099;&#1083;&#1080;</model><brand>&#1058;&#1086;&#1088;&#1088;&#1080;&#1085;&#1072;</brand><availabilities><availability storeId="PP1" available="yes" /></availabilities><price>21036</price></offer><offer sku="104308317"><model>Universal Art &#1084;&#1086;&#1076;&#1091;&#1083;&#1100;&#1085;&#1072;&#1103; &#1082;&#1072;&#1088;&#1090;&#1080;&#1085;&#1072; &#1046;&#1080;&#1074;&#1080; &#1071;&#1088;&#1082;&#1086; 90x30 &#1089;&#1084;</model><brand>Universal Art</brand><availabilities><availability storeId="PP1" available="yes" /></availabilities><price>11895</price></offer><offer sku="104248361"><model>&#1058;&#1086;&#1088;&#1088;&#1080;&#1085;&#1072; &#1084;&#1086;&#1076;&#1091;&#1083;&#1100;&#1085;&#1072;&#1103; &#1082;&#1072;&#1088;&#1090;&#1080;&#1085;&#1072; &#1050;&#1086;&#1088;&#1072;&#1073;&#1083;&#1100; 177x99 &#1089;&#1084;</model><brand>&#1058;&#1086;&#1088;&#1088;&#1080;&#1085;&#1072;</brand><availabilities><availability storeId="PP1" available="yes" /></availabilities><price>26964</price></offer><offer sku="103860611"><model>Kartina Almaty &#1084;&#1086;&#1076;&#1091;&#1083;&#1100;&#1085;&#1072;&#1103; &#1082;&#1072;&#1088;&#1090;&#1080;&#1085;&#1072; &#1050;&#1088;&#1072;&#1089;&#1085;&#1099;&#1077; &#1084;&#1072;&#1082;&#1080; 150x100 &#1089;&#1084;</model><brand>Kartina Almaty</brand><availabilities><availability storeId="PP1" available="yes" /></availabilities><price>17800</price></offer><offer sku="103958341"><model>&#1058;&#1086;&#1088;&#1088;&#1080;&#1085;&#1072; &#1084;&#1086;&#1076;&#1091;&#1083;&#1100;&#1085;&#1072;&#1103; &#1082;&#1072;&#1088;&#1090;&#1080;&#1085;&#1072; &#1062;&#1074;&#1077;&#1090;&#1099; 105x70 &#1089;&#1084;</model><brand>&#1058;&#1086;&#1088;&#1088;&#1080;&#1085;&#1072;</brand><availabilities><availability storeId="PP1" available="yes" /></availabilities><price>15745</price></offer><offer sku="103860636"><model>Kartina Almaty &#1084;&#1086;&#1076;&#1091;&#1083;&#1100;&#1085;&#1072;&#1103; &#1082;&#1072;&#1088;&#1090;&#1080;&#1085;&#1072; &#1055;&#1072;&#1088;&#1080;&#1078; 155x97 &#1089;&#1084;</model><brand>Kartina Almaty</brand><availabilities><availability storeId="PP1" available="yes" /></availabilities><price>17703</price></offer><offer sku="103867256"><model>&#1058;&#1086;&#1088;&#1088;&#1080;&#1085;&#1072; &#1084;&#1086;&#1076;&#1091;&#1083;&#1100;&#1085;&#1072;&#1103; &#1082;&#1072;&#1088;&#1090;&#1080;&#1085;&#1072; &#1062;&#1074;&#1077;&#1090;&#1099; 276x99 &#1089;&#1084;</model><brand>&#1058;&#1086;&#1088;&#1088;&#1080;&#1085;&#1072;</brand><availabilities><availability storeId="PP1" available="yes" /></availabilities><price>26968</price></offer><offer sku="103538549"><model>Kartina Almaty &#1084;&#1086;&#1076;&#1091;&#1083;&#1100;&#1085;&#1072;&#1103; &#1082;&#1072;&#1088;&#1090;&#1080;&#1085;&#1072; &#1041;&#1077;&#1083;&#1099;&#1077; &#1094;&#1074;&#1077;&#1090;&#1099; &#1074; &#1095;&#1077;&#1088;&#1085;&#1086;&#1081; &#1074;&#1072;&#1079;&#1077; 90x60 &#1089;&#1084;</model><brand>Kartina Almaty</brand><availabilities><availability storeId="PP1" available="yes" /></availabilities><price>10611</price></offer><offer sku="&#160;103539198"><model>Kartina Almaty &#1082;&#1072;&#1088;&#1090;&#1080;&#1085;&#1072; BISMILLAH 70x50 &#1089;&#1084;</model><brand>Kartina Almaty</brand><availabilities><availability storeId="PP1" available="yes" /></availabilities><price>7980</price></offer><offer sku="103094731"><model>&#1048;&#1055; &#1058;&#1086;&#1088;&#1088;&#1080;&#1085;&#1072; &#1084;&#1086;&#1076;&#1091;&#1083;&#1100;&#1085;&#1072;&#1103; &#1082;&#1072;&#1088;&#1090;&#1080;&#1085;&#1072; &#1055;&#1072;&#1085;&#1090;&#1077;&#1088;&#1072; 87x54 &#1089;&#1084;</model><brand>&#1058;&#1086;&#1088;&#1088;&#1080;&#1085;&#1072;</brand><availabilities><availability storeId="PP1" available="yes" /></availabilities><price>10515</price></offer><offer sku="102995524"><model>Seven Art &#1084;&#1086;&#1076;&#1091;&#1083;&#1100;&#1085;&#1072;&#1103; &#1082;&#1072;&#1088;&#1090;&#1080;&#1085;&#1072; 80&#1093;125 &#1089;&#1084;</model><brand>Seven Art</brand><availabilities><availability storeId="PP1" available="yes" /></availabilities><price>14484</price></offer><offer sku="102973109"><model>&#1048;&#1055; &#1058;&#1086;&#1088;&#1088;&#1080;&#1085;&#1072; &#1084;&#1086;&#1076;&#1091;&#1083;&#1100;&#1085;&#1072;&#1103; &#1082;&#1072;&#1088;&#1090;&#1080;&#1085;&#1072; &#1057;&#1072;&#1082;&#1091;&#1088;&#1072; 148x99 &#1089;&#1084; + &#1087;&#1086;&#1082;&#1088;&#1099;&#1090;&#1080;&#1077; &#1083;&#1072;&#1082;&#1086;&#1084;, &#1089; &#1101;&#1092;&#1092;&#1077;&#1082;&#1090;&#1086;&#1084; &#1072;&#1083;&#1084;&#1072;&#1079;&#1085;&#1086;&#1081; &#1087;&#1099;&#1083;&#1080;</model><brand>&#1058;&#1086;&#1088;&#1088;&#1080;&#1085;&#1072;</brand><availabilities><availability storeId="PP1" available="yes" /></availabilities><price>22705</price></offer><offer sku="102845377"><model>Press House &#1082;&#1072;&#1088;&#1090;&#1080;&#1085;&#1072; &#1044;&#1077;&#1088;&#1079;&#1082;&#1080;&#1081; &#1083;&#1077;&#1074; &#1040;2 59&#1093;42 &#1089;&#1084; 42x59 &#1089;&#1084;</model><brand>Press House</brand><availabilities><availability storeId="PP1" available="yes" /></availabilities><price>6698</price></offer><offer sku="102451442"><model>&#1058;&#1086;&#1088;&#1088;&#1080;&#1085;&#1072; &#1060;&#1088;&#1091;&#1082;&#1090;&#1099; 50x160 &#1089;&#1084;</model><brand>&#1058;&#1086;&#1088;&#1088;&#1080;&#1085;&#1072;</brand><availabilities><availability storeId="PP1" available="yes" /></availabilities><price>12314</price></offer><offer sku="102738092"><model>&#1058;&#1086;&#1088;&#1088;&#1080;&#1085;&#1072; &#1040;&#1073;&#1089;&#1090;&#1088;&#1072;&#1082;&#1094;&#1080;&#1103; 54x160 &#1089;&#1084;</model><brand>&#1058;&#1086;&#1088;&#1088;&#1080;&#1085;&#1072;</brand><availabilities><availability storeId="PP1" available="yes" /></availabilities><price>18955</price></offer></offers></kaspi_catalog>